celltypegenomics/__init__.py
celltypegenomics/celltypegenomics.py
celltypegenomics/test_celltypegenomics.py
celltypegenomics/test_integration.py
celltypegenomics/data/heca_cell_types_to_ensembl.json
celltypegenomics/data/hpa_cell_types_to_ensembl.json
celltypegenomics/data/hpa_marker_genes_cell_types_to_ensembl.json
celltypegenomics/data/hpa_tissue_to_ensembl.json
celltypegenomics/data/protein_atlas_ensembl_ids.json
celltypegenomics/data/tissue_and_cell_types_to_ensembl.json
celltypegenomics-0.0.8.dist-info/METADATA
celltypegenomics-0.0.8.dist-info/WHEEL
celltypegenomics-0.0.8.dist-info/licenses/LICENSE
celltypegenomics-0.0.8.dist-info/RECORD
