Metadata-Version: 2.3
Name: celltypegenomics
Version: 0.0.8
Summary: Package for cell type genomics
Project-URL: Homepage, https://github.com/Zyron/CellTypeGenomics
Project-URL: Bug Tracker, https://github.com/Zyron/CellTypeGenomics/issues
Author-email: Lars Føleide <larsfole@stud.ntnu.no>
License-File: LICENSE
Classifier: License :: OSI Approved :: MIT License
Classifier: Operating System :: OS Independent
Classifier: Programming Language :: Python :: 3
Requires-Python: >=3.7
Requires-Dist: pandas
Requires-Dist: scipy
Requires-Dist: statsmodels
